docify_ai-1.7.0.dist-info/licenses/LICENSE
docify_tool/__init__.py
docify_tool/cli.py
docify_tool/dataset_extractor.py
docify_tool/generator.py
docify_tool/helper.py
docify_tool/prompts.py
docify_tool/scanner.py
docify_ai-1.7.0.dist-info/METADATA
docify_ai-1.7.0.dist-info/WHEEL
docify_ai-1.7.0.dist-info/entry_points.txt
docify_ai-1.7.0.dist-info/top_level.txt
docify_ai-1.7.0.dist-info/RECORD
