Metadata-Version: 2.4
Name: docify-ai
Version: 1.7.0
Summary: An AI-powered documentation generator that uses OpenAI and Gemini models to create high-quality README.md files, model cards, notebooks, tests, and boilerplate, tailored to your project’s code and structure.
Author: Shiwang Upadhyay
Author-email: shiwangupadhyay8@gmail.com
Project-URL: Homepage, https://github.com/shiwangupadhyay/docify-project
Project-URL: Repository, https://github.com/shiwangupadhyay/docify-project
Project-URL: Issues, https://github.com/shiwangupadhyay/docify-project/issues
Keywords: ai,documentation,readme-generator,tests-generator,project-structure,docker-template,cicd-workflows-template,mermaid-diagrams,openai,gemini,automation,developer-tools,cli,docstrings,notebook-generation,automatic-data-cleaning,auto-EDA,notebook-generator,model-card,model-card-generator
Classifier: Programming Language :: Python :: 3
Classifier: Operating System :: OS Independent
Classifier: Topic :: Software Development :: Documentation
Requires-Python: >=3.8
License-File: LICENSE
Requires-Dist: google-generativeai>=0.8.5
Requires-Dist: openai>=1.100.2
Dynamic: license-file
